foodsale/__init__.py
foodsale/pathfromglob.py
foodsale/skeleton.py
foodsale-0.0.6.dist-info/LICENSE.txt
foodsale-0.0.6.dist-info/METADATA
foodsale-0.0.6.dist-info/WHEEL
foodsale-0.0.6.dist-info/entry_points.txt
foodsale-0.0.6.dist-info/top_level.txt
foodsale-0.0.6.dist-info/RECORD
